dymopy/__init__.py
dymopy/client.py
tests/__init__.py
tests/test_dymopy.py
dymopy-0.1.8.dist-info/LICENSE.md
dymopy-0.1.8.dist-info/METADATA
dymopy-0.1.8.dist-info/WHEEL
dymopy-0.1.8.dist-info/top_level.txt
dymopy-0.1.8.dist-info/RECORD
