Metadata-Version: 2.1
Name: dymopy
Version: 0.1.8
Summary: API wrapper for DYMO Web Services.
Home-page: https://github.com/bill-ash/dymopy
Author: Bill Ash
Author-email: bill@overco.net
License: UNKNOWN
Project-URL: Bug Tracker, https://github.com/bill-ash/dymopy/issues
Platform: UNKNOWN
Classifier: Programming Language :: Python :: 3
Classifier: License :: OSI Approved :: MIT License
Classifier: Operating System :: OS Independent
Requires-Python: >=3.6
License-File: LICENSE.md
Requires-Dist: requests
Provides-Extra: tests
Requires-Dist: pytest ; extra == 'tests'
